[
  {
    "eventName": "CBFK - International Chessboxing Grand Prix 75kg",
    "date": "25 February 2024",
    "venue": "Almaty, Kazakhstan, Kazakhstan",
    "fights": "5"
  },
  {
    "eventName": "CBCB - Chessboxing Fight Night Vol 2",
    "date": "24 February 2024",
    "venue": "World Chess Club Berlin, Germany",
    "fights": "5"
  },
  {
    "eventName": "CBCB - Chessboxing Fight Night",
    "date": "23 November 2023",
    "venue": "World Chess Club Berlin, Germany",
    "fights": "4"
  },
  {
    "eventName": "WCBO - World Chessboxing Championships 2023",
    "date": "28 October 2023",
    "venue": "Playhall Riccione Palazzo Dello Sport, Italy",
    "fights": "49"
  },
  {
    "eventName": "CBN - Oktoberfist 23",
    "date": "07 October 2023",
    "venue": "The Dome, London, England",
    "fights": "5"
  },
  {
    "eventName": "FSB - 1st World Traditional Combat Games",
    "date": "03 October 2023",
    "venue": "Ice Palace Arena, Cheboksary, Russia",
    "fights": "5"
  },
  {
    "eventName": "FSB - International Chessboxing Grand Prix 85kg",
    "date": "09 September 2023",
    "venue": "Unknown venue 01,  Surgut, Russia",
    "fights": "3"
  },
  {
    "eventName": "LSBF - International Chessboxing Day",
    "date": "21 July 2023",
    "venue": "Šančių Sporto centras, Kauno, Lithuania, Lithuania",
    "fights": "4"
  },
  {
    "eventName": "CBOI - Asian Chessboxing Gala Night",
    "date": "07 June 2023",
    "venue": "Unknown venue 01, Kolkata, India",
    "fights": "5"
  },
  {
    "eventName": "CBOI - 2ND WCBO Indian Open Chessboxing World Cup",
    "date": "05 June 2023",
    "venue": "Unknown venue 01, Kolkata, India",
    "fights": "3"
  },
  {
    "eventName": "CBP - Intellectual Fight Club 4",
    "date": "28 May 2023",
    "venue": "Théâtre de la Mer, Sète, France",
    "fights": "4"
  },
  {
    "eventName": "FSB - International Chessboxing Grand Prix 85kg",
    "date": "08 April 2023",
    "venue": "Lesnoye sports complex, Sochi, Russia",
    "fights": "5"
  },
  {
    "eventName": "CBN - St Patricks Day Bash 2023",
    "date": "25 March 2023",
    "venue": "The Dome, London, England",
    "fights": "5"
  },
  {
    "eventName": "FSB - Open children's chessboxing tournament",
    "date": "23 February 2023",
    "venue": "Sofia Shopping mall, Moscow, Russia",
    "fights": "2"
  },
  {
    "eventName": "CBP - Intellectual Fight Club 3",
    "date": "03 February 2023",
    "venue": "Cabaret Sauvage, Paris, France",
    "fights": "4"
  },
  {
    "eventName": "FSB - International Chessboxing Grand Prix 75kg",
    "date": "14 January 2023",
    "venue": "Olympia Palace, St. Petersburg, Russia",
    "fights": "4"
  },
  {
    "eventName": "Mogul Chessboxing Championship",
    "date": "11 December 2022",
    "venue": "Galen Center, Los Angeles, United States",
    "fights": "7"
  },
  {
    "eventName": "CBN - Seasons Beatings 2022",
    "date": "10 December 2022",
    "venue": "The Dome, London, England",
    "fights": "4"
  },
  {
    "eventName": "WCBO - World Chessboxing Championships 2022",
    "date": "16 November 2022",
    "venue": "Palmet Beach Resort Hotel, Antalya Turkey, Turkey",
    "fights": "41"
  },
  {
    "eventName": "CBP - Intellectual Fight Club - Chessboxing Night",
    "date": "01 October 2022",
    "venue": "Cabaret Sauvage, Paris, France",
    "fights": "4"
  },
  {
    "eventName": "FSB - International Chessboxing Grand Prix 65kg",
    "date": "17 September 2022",
    "venue": "Cheboksary Sports School, Russia",
    "fights": "5"
  },
  {
    "eventName": "FISP International Chessboxing Show",
    "date": "03 June 2022",
    "venue": "Piazza Ducale, Vigevano, Italy",
    "fights": "4"
  },
  {
    "eventName": "CBN - Chessboxing Mayhem",
    "date": "28 May 2022",
    "venue": "The Dome, London, England",
    "fights": "4"
  },
  {
    "eventName": "FSHB Champion Belt of Russia",
    "date": "06 March 2022",
    "venue": "Unknown venue 01, St Petersburg, Russia",
    "fights": "1"
  },
  {
    "eventName": "Alpari Cup Chessboxing Tournament",
    "date": "10 February 2022",
    "venue": "5 Element gym, Moscow, Russia",
    "fights": "2"
  },
  {
    "eventName": "CB Iran - 6th National Chessboxing Championships",
    "date": "21 January 2022",
    "venue": "Kish Island, Iran, Iran",
    "fights": "0"
  },
  {
    "eventName": "CBN - Seasons Beatings 2021",
    "date": "11 December 2021",
    "venue": "The Dome, London, England",
    "fights": "4"
  },
  {
    "eventName": "CBOI - 4th Federation Cup, Jitendra Sharma Memorial",
    "date": "27 October 2021",
    "venue": "Digha Sea Beach, West Bengal, India",
    "fights": "0"
  },
  {
    "eventName": "CBCB - Schachboxen im Goldenen Haus",
    "date": "09 October 2021",
    "venue": "Das Goldene Haus, Germany",
    "fights": "3"
  },
  {
    "eventName": "CBOI - National Ranking Chessboxing Tournament",
    "date": "03 October 2021",
    "venue": "Digha Sea Beach, West Bengal, India",
    "fights": "0"
  },
  {
    "eventName": "FCC - Nordic Chessboxing Fight Night",
    "date": "02 October 2021",
    "venue": "Paasitorni Main Hall, Helsinki, Finland",
    "fights": "4"
  },
  {
    "eventName": "LSBF - First Lithuanian Open Chess Boxing Championship",
    "date": "21 August 2021",
    "venue": "Geležinės pir&scaron;tinės, Kaunas, Lithuania, Lithuania",
    "fights": "4"
  },
  {
    "eventName": "CBOI - 9th National Chessboxing Championship 2021",
    "date": "17 August 2021",
    "venue": "The Circle Club, Kolkata, India",
    "fights": "0"
  },
  {
    "eventName": "CBOI - 9th West Bengal State Chessboxing Championship",
    "date": "07 February 2021",
    "venue": "Das School of Martial Arts complex, Kolkata, India",
    "fights": "0"
  },
  {
    "eventName": "LSBF - Dymer cup",
    "date": "11 October 2020",
    "venue": "Strikers gym, Lithuania, Lithuania",
    "fights": "5"
  },
  {
    "eventName": "LCB - 36 Clash of Kings 2020",
    "date": "26 July 2020",
    "venue": "The Dome, London, England",
    "fights": "4"
  },
  {
    "eventName": "LCB - St Patricks Day Bash 2020",
    "date": "14 March 2020",
    "venue": "The Dome, London, England",
    "fights": "4"
  },
  {
    "eventName": "Ignition Amsterdam",
    "date": "08 January 2020",
    "venue": "Paradiso, Amsterdam, Netherlands",
    "fights": "2"
  },
  {
    "eventName": "WCBO - World Chessboxing Championships 2019",
    "date": "15 December 2019",
    "venue": "Palmet Beach Resort Hotel, Antalya Turkey, Turkey",
    "fights": "44"
  },
  {
    "eventName": "LCB - Seasons Beatings 2019",
    "date": "07 December 2019",
    "venue": "The Dome, London, England",
    "fights": "5"
  },
  {
    "eventName": "CBP - Chessboxing Fights Paris #1",
    "date": "09 November 2019",
    "venue": "Cabaret Sauvage, Paris, France",
    "fights": "3"
  },
  {
    "eventName": "LSBF - Introducing Chessboxing to Lithuania",
    "date": "09 October 2019",
    "venue": "Strikers gym, Lithuania, Lithuania",
    "fights": "2"
  },
  {
    "eventName": "LCB - Oktoberfist 2019",
    "date": "05 October 2019",
    "venue": "The Dome, London, England",
    "fights": "4"
  },
  {
    "eventName": "CBOI - 8th National Chessboxing Championship 2019",
    "date": "25 August 2019",
    "venue": "Kshudiram Anushilan Kendra, Kolkata, India, India",
    "fights": "0"
  },
  {
    "eventName": "TCBF - Turkish Chessboxing Championship 2019",
    "date": "17 August 2019",
    "venue": "Altunhisar Spor Salonu, Altunhisar, Turkey",
    "fights": "1"
  },
  {
    "eventName": "CBOI - 4th Federation Cup - National Inter School & Inter College Chess Boxing Championship 2019",
    "date": "05 May 2019",
    "venue": "Angel College of Engineering and Technology, Tamil Nadu, India",
    "fights": "0"
  },
  {
    "eventName": "LCB - St Patricks Day Bash 2019",
    "date": "16 March 2019",
    "venue": "The Dome, London, England",
    "fights": "4"
  },
  {
    "eventName": "CBOI - 7th National Chessboxing Championship",
    "date": "31 December 2018",
    "venue": "NSRCC Sports Complex, Agartala, India",
    "fights": "0"
  },
  {
    "eventName": "LCB - Seasons Beatings 2018",
    "date": "08 December 2018",
    "venue": "The Dome, London, England",
    "fights": "5"
  },
  {
    "eventName": "FISP - Italian middleweight title of chessboxing",
    "date": "02 December 2018",
    "venue": "Teatro Principe, Milan, Italy",
    "fights": "1"
  },
  {
    "eventName": "WCBO - 2nd Amateur World Championship 2018",
    "date": "29 July 2018",
    "venue": "Kshudiram Anushilan Kendra, Kolkata, India, India",
    "fights": "2"
  },
  {
    "eventName": "LCB - Summer Special 2018 Thunder Dome",
    "date": "23 June 2018",
    "venue": "The Dome, London, England",
    "fights": "3"
  },
  {
    "eventName": "CBOI - 3rd Federation Cup - National Inter School & Inter College Chess Boxing Championship 2018",
    "date": "31 March 2018",
    "venue": "Bajaj Municipal School, Mumbai, India",
    "fights": "0"
  },
  {
    "eventName": "The International ChessBoxing Cup",
    "date": "28 March 2018",
    "venue": "Sokolniki Exhibition and Convention Center, Moscow, Russia",
    "fights": "6"
  },
  {
    "eventName": "CBCB - Intellectual Fight Club X",
    "date": "16 March 2018",
    "venue": "Festsaal Kreuzberg, Berlin, Germany",
    "fights": "3"
  },
  {
    "eventName": "CB Iran - 4th National Chessboxing Championships",
    "date": "23 February 2018",
    "venue": "Unknown venue 01, Tehran, Iran",
    "fights": "0"
  },
  {
    "eventName": "CBOI - 6th National Chessboxing Championship",
    "date": "28 January 2018",
    "venue": "Mahatma Gandhi Indoor Stadium, Tamil Nadu, India",
    "fights": "0"
  },
  {
    "eventName": "CBOI - Tamil Nadu State Chessboxing Championship 2017-2018",
    "date": "17 December 2017",
    "venue": "St. Joseph's Matriculation School, Tamil Nadu, India",
    "fights": "0"
  },
  {
    "eventName": "CBCB - Intellectual Fight Club IX",
    "date": "15 December 2017",
    "venue": "Glashaus, Berlin, Germany",
    "fights": "4"
  },
  {
    "eventName": "MCBF - Moscow ChessBoxing Championship 2017",
    "date": "26 November 2017",
    "venue": "Sektsia, Moscow, Russia",
    "fights": "4"
  },
  {
    "eventName": "CBOI - 6th West Bengal State Chessboxing Championship",
    "date": "19 November 2017",
    "venue": "Sports Authority Of India, Kolkata, India",
    "fights": "0"
  },
  {
    "eventName": "LCB - Norwich Yellobric Fundraiser 2017",
    "date": "21 October 2017",
    "venue": "OPEN, Norwich, England",
    "fights": "4"
  },
  {
    "eventName": "CBOI - 2nd Tripura State Chessboxing Championship 2017",
    "date": "10 September 2017",
    "venue": "Unknown venue 01, Udaipur, India",
    "fights": "0"
  },
  {
    "eventName": "CBCB - Intellectual Fight Club VIII",
    "date": "02 June 2017",
    "venue": "Kulhaus, Berlin, Germany",
    "fights": "3"
  },
  {
    "eventName": "WCBO - Chess Boxing Amateur World Championship 2017",
    "date": "15 April 2017",
    "venue": "Kshudiram Anushilan Kendra, Kolkata, India, India",
    "fights": "0"
  },
  {
    "eventName": "CBCB - Intellectual Fight Club VII",
    "date": "07 April 2017",
    "venue": "Festsaal Kreuzberg, Berlin, Germany",
    "fights": "3"
  },
  {
    "eventName": "LCB - Pity The Fool 2016 Brexit Belt",
    "date": "01 April 2017",
    "venue": "York Hall, London, England",
    "fights": "4"
  },
  {
    "eventName": "CBOI - 2nd Federation Cup - National Inter School & Inter College Chess Boxing Championship 2017",
    "date": "13 March 2017",
    "venue": "Dahisar Sports Foundation, Mumbai, India",
    "fights": "0"
  },
  {
    "eventName": "CBOI - 5th National Chessboxing Championship 2016",
    "date": "18 December 2016",
    "venue": "Maharishi Vidya Mandir School, India",
    "fights": "0"
  },
  {
    "eventName": "LCB - Season's Beatings 2016",
    "date": "17 December 2016",
    "venue": "York Hall, London, England",
    "fights": "5"
  },
  {
    "eventName": "MCBF - Moscow ChessBoxing Championship 2016",
    "date": "11 December 2016",
    "venue": "Moscow ChessBoxing club, Russia",
    "fights": "0"
  },
  {
    "eventName": "CBCB - Intellectual Fight Club VI",
    "date": "26 November 2016",
    "venue": "Kaufhaus Jandorf, Germany",
    "fights": "4"
  },
  {
    "eventName": "FISP - 1st Regional Lombard Championships",
    "date": "05 November 2016",
    "venue": "Heracles Gymnasium, Italy",
    "fights": "6"
  },
  {
    "eventName": "CBGM - Investor Pitch event for TBWA",
    "date": "30 September 2016",
    "venue": "Pfefferberg Haus 13, Germany",
    "fights": "2"
  },
  {
    "eventName": "CBOI - CBAM - Chessboxing Mumbai Mayor Cup",
    "date": "30 September 2016",
    "venue": "Unknown venue 01, Mumbai, India",
    "fights": "0"
  },
  {
    "eventName": "CB Iran - 3rd National Chessboxing Championships",
    "date": "26 August 2016",
    "venue": "Unknown venue 01, Tehran, Iran",
    "fights": "0"
  },
  {
    "eventName": "LCB - Summer Special 2016",
    "date": "18 June 2016",
    "venue": "York Hall, London, England",
    "fights": "5"
  },
  {
    "eventName": "FISP - Chessboxing Exhibition at Festa di Primavera",
    "date": "24 April 2016",
    "venue": "Festa di Primavera, Italy",
    "fights": "0"
  },
  {
    "eventName": "CBCB - Intellectual Fight Club V",
    "date": "23 April 2016",
    "venue": "Platoon Kunsthalle, Berlin, Germany",
    "fights": "3"
  },
  {
    "eventName": "LCB - Season Opener 2016",
    "date": "02 April 2016",
    "venue": "York Hall, London, England",
    "fights": "3"
  },
  {
    "eventName": "CBOI - Federation Cup, National Ranking & National Seminar",
    "date": "27 March 2016",
    "venue": "Sports Authority Of India, Kolkata, India",
    "fights": "0"
  },
  {
    "eventName": "CBOI - Tamilnadu State Chessboxing Championship",
    "date": "21 February 2016",
    "venue": "Unknown venue 01, Tamil Nadu, India",
    "fights": "0"
  },
  {
    "eventName": "LACBC - Bringing Back Broadway Event 2016",
    "date": "30 January 2016",
    "venue": "Broadway Theater District, Los Angeles, United States",
    "fights": "3"
  },
  {
    "eventName": "CBCB - Intellectual Fight Club IV",
    "date": "12 December 2015",
    "venue": "Platoon Kunsthalle, Berlin, Germany",
    "fights": "3"
  },
  {
    "eventName": "MCBF - Moscow ChessBoxing Championship 2015",
    "date": "06 December 2015",
    "venue": "Moscow ChessBoxing club, Russia",
    "fights": "3"
  },
  {
    "eventName": "LCB - York Hall Chessboxing Spectacular 2015",
    "date": "28 November 2015",
    "venue": "York Hall, London, England",
    "fights": "4"
  },
  {
    "eventName": "Fight Knight",
    "date": "22 November 2015",
    "venue": "Pink Boxing, Melbourne, Australia, Australia",
    "fights": "1"
  },
  {
    "eventName": "FISP - International Chessboxing Show",
    "date": "24 October 2015",
    "venue": "Hurricane, Italy, Italy",
    "fights": "5"
  },
  {
    "eventName": "CBCB - Intellectual Fight Club III",
    "date": "09 October 2015",
    "venue": "Platoon Kunsthalle, Berlin, Germany",
    "fights": "2"
  },
  {
    "eventName": "CBOI - 4th Sub-Junior & Junior National Chessboxing Championship",
    "date": "08 October 2015",
    "venue": "Maharashtra Chess-Boxing, India",
    "fights": "0"
  },
  {
    "eventName": "CQ CBC - Exhibition Fight Night",
    "date": "08 August 2015",
    "venue": "Rhino MMA, Rockhampton, Australia",
    "fights": "1"
  },
  {
    "eventName": "CBCB - Intellectual Fight Club II",
    "date": "17 July 2015",
    "venue": "Platoon Kunsthalle, Berlin, Germany",
    "fights": "3"
  },
  {
    "eventName": "CBOI - 4th Senior National Chessboxing Championship",
    "date": "28 June 2015",
    "venue": "Sports Authority Of India, Kolkata, India",
    "fights": "0"
  },
  {
    "eventName": "CB Iran - 2nd National Chessboxing Championships",
    "date": "15 June 2015",
    "venue": "Iran Chessboxing House, Shiraz, Iran",
    "fights": "0"
  },
  {
    "eventName": "CBOI - 1st Tripura State Chessboxing Championship & Seminar",
    "date": "14 June 2015",
    "venue": "Bichitra Hall, Tripura, India",
    "fights": "0"
  },
  {
    "eventName": "LCB - GrandMaster BASH 2015",
    "date": "13 June 2015",
    "venue": "Scala, London, England",
    "fights": "3"
  },
  {
    "eventName": "FCC - 1st Chessboxing Fight in Finland",
    "date": "06 June 2015",
    "venue": "Savate Club, Helsinki, Finland",
    "fights": "1"
  },
  {
    "eventName": "FISP - Public exhibition of chess boxing at Mongrando EXPO",
    "date": "24 May 2015",
    "venue": "Mongrando EXPO 2015, Italy",
    "fights": "3"
  },
  {
    "eventName": "CBCB - Intellectual Fight Club",
    "date": "09 May 2015",
    "venue": "Platoon Kunsthalle, Berlin, Germany",
    "fights": "3"
  },
  {
    "eventName": "CBOI - National Chessboxing Ranking Competition in Darjeeling",
    "date": "05 April 2015",
    "venue": "Unknown venue 01, Darjeeling, India",
    "fights": "0"
  },
  {
    "eventName": "CBOI - 4th West Bengal State Chessboxing Championship",
    "date": "31 March 2015",
    "venue": "Kidderpore School of Physical Culture, Kolkata, India",
    "fights": "0"
  },
  {
    "eventName": "LCB - Season Opener 2015",
    "date": "14 March 2015",
    "venue": "Scala, London, England",
    "fights": "4"
  },
  {
    "eventName": "CB Iran - 1st National Chessboxing Championships",
    "date": "27 February 2015",
    "venue": "Iran Chessboxing House, Shiraz, Iran",
    "fights": "0"
  },
  {
    "eventName": "LACBC - Night on Broadway #ThinkTankTower Chessboxing Event",
    "date": "31 January 2015",
    "venue": "Tower Theatre, Los Angeles, United States",
    "fights": "0"
  },
  {
    "eventName": "CBOI - Telangana State Chessboxing Championship",
    "date": "31 January 2015",
    "venue": "Chitramayee Gallery of Art, Hyderabad, India",
    "fights": "0"
  },
  {
    "eventName": "CBOI - Tamil Nadu State Chessboxing Championship",
    "date": "30 January 2015",
    "venue": "Mahatma Gandhi Indoor Stadium, Tamil Nadu, India",
    "fights": "0"
  },
  {
    "eventName": "CBOI - Interschool & College National Chess-Boxing Championship 2014-15",
    "date": "11 January 2015",
    "venue": "Unknown venue 01, Mumbai, India",
    "fights": "0"
  },
  {
    "eventName": "LCB - International Chessboxing 2014 Seasons Climax",
    "date": "13 December 2014",
    "venue": "Scala, London, England",
    "fights": "4"
  },
  {
    "eventName": "CBOI - 1st Kerala State Inter-School Championships",
    "date": "22 November 2014",
    "venue": "Unknown venue 01, Kerala, India",
    "fights": "0"
  },
  {
    "eventName": "World Chessboxing Championships 2014 - Intellectual Fight Night",
    "date": "21 November 2014",
    "venue": "Columbiahalle, Berlin, Germany",
    "fights": "3"
  },
  {
    "eventName": "LCB - International Chessboxing 2014 Crazy Horses",
    "date": "11 October 2014",
    "venue": "Scala, London, England",
    "fights": "4"
  },
  {
    "eventName": "CBOI - International Chessboxing Seminar",
    "date": "31 August 2014",
    "venue": "Kshudiram Anushilan Kendra, Kolkata, India, India",
    "fights": "0"
  },
  {
    "eventName": "CBOI - 1st CBOI Federation Cup",
    "date": "30 August 2014",
    "venue": "Unknown venue 01, Kolkata, India",
    "fights": "0"
  },
  {
    "eventName": "CBCB - Chessboxing Fight Night",
    "date": "16 August 2014",
    "venue": "Platoon Kunsthalle, Berlin, Germany",
    "fights": "1"
  },
  {
    "eventName": "LACBC - Chessboxing for Charity: Life, Liberty, and the Pursuit of Philanthropy",
    "date": "03 July 2014",
    "venue": "Think Tank Gallery, Los Angeles, United States",
    "fights": "2"
  },
  {
    "eventName": "LCB - International Chessboxing 2014 The Italian Job",
    "date": "14 June 2014",
    "venue": "Scala, London, England",
    "fights": "3"
  },
  {
    "eventName": "CBOI - 3rd National Chessboxing Championship (2014-2015)",
    "date": "25 May 2014",
    "venue": "Unknown venue 01, Jodhpur, India",
    "fights": "0"
  },
  {
    "eventName": "Oracle Cancer Trust Chessboxing Gala 2014",
    "date": "22 May 2014",
    "venue": "Grange St Paul's Hotel, London, England",
    "fights": "3"
  },
  {
    "eventName": "Yellobric Chessboxing Fundraiser 2014",
    "date": "16 May 2014",
    "venue": "Chelsea Old Town Hall, London, England",
    "fights": "4"
  },
  {
    "eventName": "FISP - Luci i Stelle",
    "date": "24 April 2014",
    "venue": "Shocking Luxury Club, Milan, Italy",
    "fights": "3"
  },
  {
    "eventName": "LCB - Season Opener 2014",
    "date": "12 April 2014",
    "venue": "Scala, London, England",
    "fights": "4"
  },
  {
    "eventName": "LA Chess Boxing - Coffeegraph Edition",
    "date": "20 December 2013",
    "venue": "Think Tank Gallery, Los Angeles, United States",
    "fights": "2"
  },
  {
    "eventName": "LCB - International Chessboxing 2013 Seasons Climax",
    "date": "14 December 2013",
    "venue": "Scala, London, England",
    "fights": "3"
  },
  {
    "eventName": "WCBO - World Chessboxing Championships 2013",
    "date": "28 November 2013",
    "venue": "Izvestia Hall, Moscow, Russia",
    "fights": "3"
  },
  {
    "eventName": "The Lost Lectures",
    "date": "23 November 2013",
    "venue": "York Hall, London, England",
    "fights": "1"
  },
  {
    "eventName": "CBOI - INDIAN Team Selection for World Chessboxing Championship",
    "date": "20 October 2013",
    "venue": "Unknown venue 01, Kolkata, India",
    "fights": "0"
  },
  {
    "eventName": "LCB - Wild Bulls 2013",
    "date": "12 October 2013",
    "venue": "Scala, London, England",
    "fights": "4"
  },
  {
    "eventName": "Brain vs Pain Tour - Exeter",
    "date": "04 August 2013",
    "venue": "Club Rococo, Exeter, England",
    "fights": "2"
  },
  {
    "eventName": "CBOI - 2nd Indian National Chessboxing Championship",
    "date": "28 July 2013",
    "venue": "Mahatma Gandhi Indoor Stadium, Tamil Nadu, India",
    "fights": "0"
  },
  {
    "eventName": "CBOI - 2nd Tamilnadu State Chessboxing Camp",
    "date": "15 June 2013",
    "venue": "Mahatma Gandhi Indoor Stadium, Tamil Nadu, India",
    "fights": "0"
  },
  {
    "eventName": "CBCB - Club Fights at Chess Boxing Club Berlin Gym",
    "date": "14 June 2013",
    "venue": "Franz-Mett Sporthalle, Berlin, Germany",
    "fights": "2"
  },
  {
    "eventName": "LACBO - Gleason's Gym Event",
    "date": "09 June 2013",
    "venue": "Gleason's Gym, New York, United States",
    "fights": "1"
  },
  {
    "eventName": "LCB - Kings Of The Ring 2013",
    "date": "08 June 2013",
    "venue": "Scala, London, England",
    "fights": "4"
  },
  {
    "eventName": "LACBC - Beauty and the Beasts",
    "date": "25 May 2013",
    "venue": "Fortune Gym, Los Angeles, United States",
    "fights": "2"
  },
  {
    "eventName": "Chess Boxing Charity Gala",
    "date": "27 April 2013",
    "venue": "Newcastle Civic Centre, England",
    "fights": "1"
  },
  {
    "eventName": "CBOI - National Chessboxing Camp & referee Seminar",
    "date": "07 April 2013",
    "venue": "C.L.W, Burdwan, India",
    "fights": "0"
  },
  {
    "eventName": "LCB - Grand Prix Season Opener 2013 Brain vs Pain",
    "date": "23 March 2013",
    "venue": "Scala, London, England",
    "fights": "4"
  },
  {
    "eventName": "Tuxedo Tyrants Present \"Brain meets Brawn\"",
    "date": "10 February 2013",
    "venue": "Private Warehouse Location in Downtown LA, United States",
    "fights": "3"
  },
  {
    "eventName": "Exhibition match at Artcurial, Paris",
    "date": "01 February 2013",
    "venue": "Artcurial, Paris, France",
    "fights": "1"
  },
  {
    "eventName": "CBOI - 1st National Chessboxing Championship (2012-2013)",
    "date": "13 January 2013",
    "venue": "Kshudiram Anushilan Kendra, Kolkata, India, India",
    "fights": "0"
  },
  {
    "eventName": "LCB - Season Finale 2012: Spain vs. The World",
    "date": "08 December 2012",
    "venue": "Scala, London, England",
    "fights": "4"
  },
  {
    "eventName": "LCB - Battle Royale 2012",
    "date": "10 October 2012",
    "venue": "Royal Albert Hall, London, England",
    "fights": "3"
  },
  {
    "eventName": "LCB - Heavyweight Tournament 2012: Prizefight Knight",
    "date": "29 September 2012",
    "venue": "Scala, London, England",
    "fights": "4"
  },
  {
    "eventName": "Andrew McGregor’s 33rd birthday party",
    "date": "22 September 2012",
    "venue": "The Red Barn, Los Angeles, United States",
    "fights": "1"
  },
  {
    "eventName": "CBCB Berlin Championships",
    "date": "29 July 2012",
    "venue": "Platoon Kunsthalle, Berlin, Germany",
    "fights": "3"
  },
  {
    "eventName": "CBOI - National Chessboxing Training Camp & Seminar",
    "date": "13 July 2012",
    "venue": "Yuba Bharati Krirangan Auditorium, Kolkata, India",
    "fights": "0"
  },
  {
    "eventName": "CBOI - Chessboxing Demo Match, Kolkata",
    "date": "03 June 2012",
    "venue": "Unknown venue 01, Kolkata, India",
    "fights": "0"
  },
  {
    "eventName": "CBOI - Chessboxing Demo Match, Cooch Behar",
    "date": "21 April 2012",
    "venue": "Unknown venue 01, Cooch Behar, India",
    "fights": "0"
  },
  {
    "eventName": "LCB - Season Opener 2012 Two Tribes",
    "date": "10 March 2012",
    "venue": "Scala, London, England",
    "fights": "4"
  },
  {
    "eventName": "CBOI Indian Chessboxing Organisation foundation",
    "date": "27 November 2011",
    "venue": "Bakul Math park, Kolkata, India",
    "fights": "1"
  },
  {
    "eventName": "LCB - Heavyweight Decider 2011: Bobby Fischer Belt",
    "date": "11 November 2011",
    "venue": "Scala, London, England",
    "fights": "5"
  },
  {
    "eventName": "SCBO - Fight Night in Siberia",
    "date": "22 October 2011",
    "venue": "MixMax Convention center, Russia",
    "fights": "1"
  },
  {
    "eventName": "WCBO - Exhibition in Zurich",
    "date": "17 September 2011",
    "venue": "Boxschule Gebenstorf, Switzerland",
    "fights": "1"
  },
  {
    "eventName": "Battle of the Cities London vs Berlin",
    "date": "24 June 2011",
    "venue": "Tape Club, Berlin, Germany",
    "fights": "3"
  },
  {
    "eventName": "WCBO - Demonstration fight in Denmark",
    "date": "14 May 2011",
    "venue": "Kulturhus Herredsvang, Denmark",
    "fights": "1"
  },
  {
    "eventName": "Tuxedo Tyrants Charity Chessboxing Event",
    "date": "24 April 2011",
    "venue": "Private Warehouse Location in Downtown LA, United States",
    "fights": "2"
  },
  {
    "eventName": "LCB - Season Opener 2011",
    "date": "26 March 2011",
    "venue": "The Dome, London, England",
    "fights": "4"
  },
  {
    "eventName": "EVE Fanfest 2011: Brain Vs. Pain Chessboxing Match",
    "date": "25 March 2011",
    "venue": "Laugardalshöll Convention Center, Iceland",
    "fights": "1"
  },
  {
    "eventName": "LCB - International Chessboxing 2010 Season Climax",
    "date": "04 December 2010",
    "venue": "The Dome, London, England",
    "fights": "0"
  },
  {
    "eventName": "International German Championship 2010",
    "date": "06 November 2010",
    "venue": "Festsaal Kreuzberg, Berlin, Germany",
    "fights": "3"
  },
  {
    "eventName": "LCB - Beyond The Super-Dome 2010",
    "date": "16 October 2010",
    "venue": "The Dome, London, England",
    "fights": "3"
  },
  {
    "eventName": "LCB - Super-Dome II 2010",
    "date": "15 May 2010",
    "venue": "The Dome, London, England",
    "fights": "3"
  },
  {
    "eventName": "Exhibition Bout at La Tour Blanche",
    "date": "10 April 2010",
    "venue": "Tour Blanche, Paris, France",
    "fights": "1"
  },
  {
    "eventName": "LCB - International Chessboxing 2010 Super Dome",
    "date": "13 March 2010",
    "venue": "The Dome, London, England",
    "fights": "3"
  },
  {
    "eventName": "LACBO - Los Angeles Chessboxing Club Fight",
    "date": "27 February 2010",
    "venue": "Wild Card Boxing, Los Angeles, United States",
    "fights": "1"
  },
  {
    "eventName": "WCBO-GBCBO - London Chessboxing",
    "date": "04 December 2009",
    "venue": "The Dome, London, England",
    "fights": "3"
  },
  {
    "eventName": "Chessboxing Lightweight World Championship",
    "date": "28 November 2009",
    "venue": "Ivan Yarygin Palace of Sport, Krasnoyarsk,, Russia",
    "fights": "1"
  },
  {
    "eventName": "Chessboxing exhibition at Slick 2009",
    "date": "22 October 2009",
    "venue": "The Cent Quatre, Paris, France",
    "fights": "1"
  },
  {
    "eventName": "Game of Kings 2009",
    "date": "09 October 2009",
    "venue": "The Dome, London, England",
    "fights": "3"
  },
  {
    "eventName": "Velada Chess-Boxing en Salamanca",
    "date": "11 June 2009",
    "venue": "Castilla y León International Arts Festival, Spain",
    "fights": "1"
  },
  {
    "eventName": "St George's Day Chessboxing Tournament 2009",
    "date": "23 April 2009",
    "venue": "Bethnal Green Working Men's Club, London, England",
    "fights": "4"
  },
  {
    "eventName": "Chessboxing Premiere Krasnoyarsk",
    "date": "21 February 2009",
    "venue": "Siberian Federal University, Russia, Russia",
    "fights": "3"
  },
  {
    "eventName": "Kings of Combat",
    "date": "30 October 2008",
    "venue": "Bethnal Green Working Men's Club, London, England",
    "fights": "3"
  },
  {
    "eventName": "WCBO - Chessboxing Tour 2008 Cologne",
    "date": "06 September 2008",
    "venue": "Gloria Theatre, Cologne, Germany",
    "fights": "3"
  },
  {
    "eventName": "An Exhibition of CHESSBOXING",
    "date": "15 August 2008",
    "venue": "Bethnal Green Working Men's Club, London, England",
    "fights": "2"
  },
  {
    "eventName": "WCBO - Chessboxing Tour 2008 Berlin",
    "date": "05 July 2008",
    "venue": "Station, Berlin, Germany",
    "fights": "3"
  },
  {
    "eventName": "WCBO - World Light-Heavyweight Championship",
    "date": "03 November 2007",
    "venue": "Tape Club, Berlin, Germany",
    "fights": "3"
  },
  {
    "eventName": "Prenzlauer Berg 2007",
    "date": "27 June 2007",
    "venue": "Platoon Kunsthalle, Berlin, Germany",
    "fights": "4"
  },
  {
    "eventName": "Nantes 2006",
    "date": "04 November 2006",
    "venue": "La cité de Congrès, Nantes, France",
    "fights": "1"
  },
  {
    "eventName": "The Cologne Fights 2006",
    "date": "21 April 2006",
    "venue": "Gloria Theatre, Cologne, Germany",
    "fights": "2"
  },
  {
    "eventName": "Chessboxing demo at Internationale Fruhjahrbuchwoche",
    "date": "02 April 2006",
    "venue": "i-camp/neues theater, Munich, Germany",
    "fights": "1"
  },
  {
    "eventName": "1st European Chessboxing Championship",
    "date": "01 October 2005",
    "venue": "Salon Ost, Berlin, Germany",
    "fights": "1"
  },
  {
    "eventName": "The Tokyo Fight",
    "date": "17 April 2004",
    "venue": "Time and Style, Tokyo, Japan",
    "fights": "1"
  },
  {
    "eventName": "1st Chess Boxing World Championship",
    "date": "14 November 2003",
    "venue": "Paradiso, Amsterdam, Netherlands",
    "fights": "1"
  },
  {
    "eventName": "1st Chessboxing Event",
    "date": "13 September 2003",
    "venue": "Platoon Kunsthalle, Berlin, Germany",
    "fights": "1"
  }
]